{
  "cli": {
    "version": ">= 7.2.0",
    "appVersionSource": "remote"
  },
  "build": {
    "development": {
      "developmentClient": true,
      "distribution": "internal"
    },
    "preview": {
      "developmentClient": false,
      "env": {
        "EXPO_NO_UPDATES": "true"
      },
      "android": {
        "buildType": "apk",
        "image": "latest"
      }
    },
    "production": {
      "env": {
        "EXPO_NO_UPDATES": "true"
      },
      "android": {
        "buildType": "app-bundle",
        "image": "latest"
      }
    }
  },
  "submit": {
    "production": {}
  }
}